charz_gl/__init__.py
charz_gl-0.1.0.dev0.dist-info/METADATA
charz_gl-0.1.0.dev0.dist-info/WHEEL
charz_gl-0.1.0.dev0.dist-info/licenses/LICENSE.txt
charz_gl-0.1.0.dev0.dist-info/RECORD
