Metadata-Version: 2.3
Name: charz-gl
Version: 0.1.0.dev0
Summary: Graphics library built upon charz
Author-email: Havsalt <77575424+Havsalt@users.noreply.github.com>
License: MIT
Requires-Python: >=3.10
Requires-Dist: charz-core==0.1.0.dev2
